<?xml version='1.0' encoding='utf-8'?>
<ParkingSlots><Slot id="slot1" status="Occupied" vehicle_type="Bike" plate_number="KA 04  1098" entry_time="2025-03-26T16:37:18" client_name="Vittal Prabhu" exit_time="2025-03-26T18:57:18" /><Slot id="slot4" status="Occupied" vehicle_type="Car" plate_number="KA 08 SK 4321" entry_time="2025-03-26T17:16:36" client_name="Vishwanath Kambalyal" exit_time="2025-03-26T21:48:36" /><Slot id="slot1" status="Occupied" vehicle_type="Car" plate_number="KA 09 NK 2109" entry_time="2025-03-26T09:12:47" client_name="Unknown" exit_time="2025-03-26T15:19:47" /><Slot id="slot2" status="Occupied" vehicle_type="Bike" plate_number="KA 08 SK 4321" entry_time="2025-03-26T03:20:15" client_name="SHIVALING KORALLI" exit_time="2025-03-26T03:52:15" /><Slot id="slot4" status="Occupied" vehicle_type="Bike" plate_number="KA 01 AJ 9876" entry_time="2025-03-26T18:46:05" client_name="SHIVALING KORALLI" exit_time="2025-03-27T01:34:05" /><Slot id="slot3" status="Occupied" vehicle_type="Bike" plate_number="KA 01 AJ 9876" entry_time="2025-03-26T19:53:52" client_name="Unknown" exit_time="2025-03-26T22:18:52" /><Slot id="slot2" status="Occupied" vehicle_type="Car" plate_number="KA 01 AJ 9876" entry_time="2025-03-26T16:23:15" client_name="Vishwanath Kambalyal" exit_time="2025-03-26T21:45:15" /><Slot id="slot7" status="Occupied" vehicle_type="Car" plate_number="KA 07 TK 5432" entry_time="2025-03-26T10:36:25" client_name="Unknown" exit_time="2025-03-26T11:55:25" /><Slot id="slot6" status="Occupied" vehicle_type="Car" plate_number="KA 08 SK 4321" entry_time="2025-03-26T13:40:54" client_name="Vishwanath Kambalyal" exit_time="2025-03-26T15:37:54" /><Slot id="slot4" status="Occupied" vehicle_type="Bike" plate_number="KA 09 NK 2109" entry_time="2025-03-26T17:31:19" client_name="Unknown" exit_time="2025-03-26T21:41:19" /><Slot id="slot3" status="Occupied" vehicle_type="Bike" plate_number="KA 04  1098" entry_time="2025-03-26T23:16:12" client_name="SHIVALING KORALLI" exit_time="2025-03-27T00:11:12" /><Slot id="slot5" status="Occupied" vehicle_type="Car" plate_number="KA 03 AJ 8717" entry_time="2025-03-26T11:34:41" client_name="Unknown" exit_time="2025-03-26T17:59:41" /><Slot id="slot2" status="Occupied" vehicle_type="Car" plate_number="KA 04 DK 1098" entry_time="2025-03-26T17:12:05" client_name="Unknown" exit_time="2025-03-26T17:37:05" /><Slot id="slot7" status="Occupied" vehicle_type="Car" plate_number="KA 07 TK 5432" entry_time="2025-03-26T09:10:17" client_name="Unknown" exit_time="2025-03-26T15:35:17" /><Slot id="slot7" status="Occupied" vehicle_type="Car" plate_number="KA 08 SK 4321" entry_time="2025-03-26T11:50:56" client_name="SHIVALING KORALLI" exit_time="2025-03-26T18:14:56" /><Slot id="slot3" status="Occupied" vehicle_type="Car" plate_number="KA 08 SK 4321" entry_time="2025-03-26T13:00:56" client_name="Vishwanath Kambalyal" exit_time="2025-03-26T16:41:56" /><Slot id="slot5" status="Occupied" vehicle_type="Car" plate_number="KA 09 NK 2109" entry_time="2025-03-26T18:36:52" client_name="Unknown" exit_time="2025-03-27T00:29:52" /><Slot id="slot1" status="Occupied" vehicle_type="Car" plate_number="KA 01 AJ 9876" entry_time="2025-03-26T07:17:37" client_name="Vittal Prabhu" exit_time="2025-03-26T08:09:37" /><Slot id="slot1" status="Occupied" vehicle_type="Car" plate_number="KA 01 AJ 9876" entry_time="2025-03-26T11:04:02" client_name="SHIVALING KORALLI" exit_time="2025-03-26T15:53:02" /><Slot id="slot1" status="Occupied" vehicle_type="Bike" plate_number="KA 09 NK 2109" entry_time="2025-03-26T15:15:58" client_name="Unknown" exit_time="2025-03-26T18:47:58" /><Slot id="slot1" status="Occupied" vehicle_type="Bike" plate_number="KA 08 SK 4321" entry_time="2025-03-26T19:10:31" client_name="Vishwanath Kambalyal" exit_time="2025-03-26T20:06:31" /><Slot id="slot2" status="Occupied" vehicle_type="Bike" plate_number="KA 04 DK 1098" entry_time="2025-03-26T16:50:33" client_name="Unknown" exit_time="2025-03-26T19:40:33" /><Slot id="slot2" status="Occupied" vehicle_type="Car" plate_number="KA 07 TK 5432" entry_time="2025-03-26T11:39:32" client_name="Unknown" exit_time="2025-03-26T14:52:32" /><Slot id="slot8" status="Occupied" vehicle_type="Car" plate_number="KA 01 AJ 9876" entry_time="2025-03-26T06:54:43" client_name="Unknown" exit_time="2025-03-26T09:56:43" /><Slot id="slot8" status="Occupied" vehicle_type="Car" plate_number="KA 08 SK 4321" entry_time="2025-03-26T13:06:43" client_name="SHIVALING KORALLI" exit_time="2025-03-26T20:25:43" /><Slot id="slot4" status="Occupied" vehicle_type="Car" plate_number="KA 01 AJ 9876" entry_time="2025-03-26T04:31:04" client_name="Vishwanath Kambalyal" exit_time="2025-03-26T12:07:04" /><Slot id="slot6" status="Occupied" vehicle_type="Car" plate_number="KA 04 DK 1098" entry_time="2025-03-26T08:51:27" client_name="Unknown" exit_time="2025-03-26T12:07:27" /><Slot id="slot3" status="Occupied" vehicle_type="Car" plate_number="KA 04 BK 4162" entry_time="2025-03-26T13:51:41" client_name="Unknown" exit_time="2025-03-26T20:39:41" /><Slot id="slot6" status="Occupied" vehicle_type="Car" plate_number="KA 08 SK 4321" entry_time="2025-03-26T07:04:51" client_name="Unknown" exit_time="2025-03-26T13:28:51" /><Slot id="slot4" status="Occupied" vehicle_type="Car" plate_number="KA 04 DK 1098" entry_time="2025-03-26T06:12:35" client_name="SHIVALING KORALLI" exit_time="2025-03-26T08:41:35" /><Slot id="slot4" status="Occupied" vehicle_type="Car" plate_number="KA 09 NK 2109" entry_time="2025-03-26T07:44:58" client_name="Unknown" exit_time="2025-03-26T11:07:58" /><Slot id="slot2" status="Occupied" vehicle_type="Car" plate_number="KA 08 SK 4321" entry_time="2025-03-26T05:30:49" client_name="Unknown" exit_time="2025-03-26T05:54:49" /></ParkingSlots>